{
    "id": "29371",
    "ident": "ESSZ",
    "type": "small_airport",
    "name": "Vängsö Airport",
    "latitude_deg": "59.10110092163086",
    "longitude_deg": "17.21109962463379",
    "elevation_ft": "",
    "continent": "EU",
    "iso_country": "SE",
    "iso_region": "SE-D",
    "municipality": "Vängsö",
    "scheduled_service": "no",
    "gps_code": "ESSZ",
    "iata_code": "",
    "local_code": "",
    "home_link": "",
    "wikipedia_link": "",
    "keywords": "",
    "runways": [
        {
            "id": "506957",
            "airport_ref": "29371",
            "airport_ident": "ESSZ",
            "length_ft": "2230",
            "width_ft": "98",
            "surface": "Grass",
            "lighted": "1",
            "closed": "0",
            "le_ident": "12",
            "le_latitude_deg": "",
            "le_longitude_deg": "",
            "le_elevation_ft": "",
            "le_heading_degT": "",
            "le_displaced_threshold_ft": "",
            "he_ident": "30",
            "he_latitude_deg": "",
            "he_longitude_deg": "",
            "he_elevation_ft": "",
            "he_heading_degT": "",
            "he_displaced_threshold_ft": ""
        }
    ]
}