{
    "id": "35094",
    "ident": "RU-4339",
    "type": "medium_airport",
    "name": "Tambov Air Base",
    "latitude_deg": "52.700626373291016",
    "longitude_deg": "41.374168395996094",
    "elevation_ft": "554",
    "continent": "EU",
    "iso_country": "RU",
    "iso_region": "RU-TAM",
    "municipality": "Tambov",
    "scheduled_service": "no",
    "gps_code": "",
    "iata_code": "",
    "local_code": "",
    "home_link": "",
    "wikipedia_link": "https://en.wikipedia.org/wiki/Tambov_(air_base)",
    "keywords": "",
    "runways": [
        {
            "id": "507507",
            "airport_ref": "35094",
            "airport_ident": "RU-4339",
            "length_ft": "8202",
            "width_ft": "157",
            "surface": "CON",
            "lighted": "1",
            "closed": "0",
            "le_ident": "16",
            "le_latitude_deg": "",
            "le_longitude_deg": "",
            "le_elevation_ft": "",
            "le_heading_degT": "",
            "le_displaced_threshold_ft": "",
            "he_ident": "34",
            "he_latitude_deg": "",
            "he_longitude_deg": "",
            "he_elevation_ft": "",
            "he_heading_degT": "",
            "he_displaced_threshold_ft": ""
        }
    ]
}