{
    "id": "6500",
    "ident": "UMMM",
    "type": "closed",
    "name": "Minsk 1 Airport",
    "latitude_deg": "53.864498",
    "longitude_deg": "27.5397",
    "elevation_ft": "748",
    "continent": "EU",
    "iso_country": "BY",
    "iso_region": "BY-MI",
    "municipality": "Minsk",
    "scheduled_service": "no",
    "gps_code": "",
    "iata_code": "",
    "local_code": "",
    "home_link": "",
    "wikipedia_link": "https://en.wikipedia.org/wiki/Minsk-1",
    "keywords": "UMMM, UMMM, MHP",
    "runways": [
        {
            "id": "233751",
            "airport_ref": "6500",
            "airport_ident": "UMMM",
            "length_ft": "",
            "width_ft": "",
            "surface": "CLOSED",
            "lighted": "0",
            "closed": "0",
            "le_ident": ".",
            "le_latitude_deg": "",
            "le_longitude_deg": "",
            "le_elevation_ft": "",
            "le_heading_degT": "",
            "le_displaced_threshold_ft": "",
            "he_ident": ".",
            "he_latitude_deg": "",
            "he_longitude_deg": "",
            "he_elevation_ft": "",
            "he_heading_degT": "",
            "he_displaced_threshold_ft": ""
        }
    ]
}